availabledatasource/__init__.py
availabledatasource/fetch_data.py
availabledatasource-1.0.0.dist-info/METADATA
availabledatasource-1.0.0.dist-info/WHEEL
availabledatasource-1.0.0.dist-info/top_level.txt
availabledatasource-1.0.0.dist-info/RECORD
