Metadata-Version: 2.1
Name: availabledatasource
Version: 1.0.0
Summary: Testing installation of Package
Home-page: https://infygithub.ad.infosys.com/veena-devipalamuri/JupyterIntegration.git
Author: auth
Author-email: author@email.com
License: MIT
Platform: UNKNOWN
